{
  "main": {
    "id": "88c15d42425db22b",
    "type": "split",
    "children": [
      {
        "id": "730b0b83f4269cdf",
        "type": "tabs",
        "children": [
          {
            "id": "5c9e6c3f03135918",
            "type": "leaf",
            "state": {
              "type": "markdown",
              "state": {
                "file": "Welcome.md",
                "mode": "source",
                "source": false
              },
              "icon": "lucide-file",
              "title": "Welcome"
            }
          },
          {
            "id": "0c526fe2d45a6321",
            "type": "leaf",
            "state": {
              "type": "markdown",
              "state": {
                "file": "Japaneese/Okkonomeyaki.md",
                "mode": "source",
                "source": false
              },
              "icon": "lucide-file",
              "title": "Okkonomeyaki"
            }
          }
        ],
        "currentTab": 1
      },
      {
        "id": "e50fb5ed2d6ee910",
        "type": "tabs",
        "children": [
          {
            "id": "b7c929ac3403cf36",
            "type": "leaf",
            "state": {
              "type": "graph",
              "state": {},
              "icon": "lucide-git-fork",
              "title": "Graph view"
            }
          }
        ]
      }
    ],
    "direction": "vertical"
  },
  "left": {
    "id": "4649a9c1427034d9",
    "type": "split",
    "children": [
      {
        "id": "52930998be61cfa9",
        "type": "tabs",
        "children": [
          {
            "id": "b6dd03f5b55534bd",
            "type": "leaf",
            "state": {
              "type": "file-explorer",
              "state": {
                "sortOrder": "alphabetical",
                "autoReveal": false
              },
              "icon": "lucide-folder-closed",
              "title": "Files"
            }
          },
          {
            "id": "83c05a308282b8ad",
            "type": "leaf",
            "state": {
              "type": "search",
              "state": {
                "query": "",
                "matchingCase": false,
                "explainSearch": false,
                "collapseAll": false,
                "extraContext": false,
                "sortOrder": "alphabetical"
              },
              "icon": "lucide-search",
              "title": "Search"
            }
          },
          {
            "id": "ef0e6075075f162d",
            "type": "leaf",
            "state": {
              "type": "bookmarks",
              "state": {},
              "icon": "lucide-bookmark",
              "title": "Bookmarks"
            }
          }
        ]
      }
    ],
    "direction": "horizontal",
    "width": 300
  },
  "right": {
    "id": "d84b6c08ee05ad05",
    "type": "split",
    "children": [
      {
        "id": "dafd01ebdc55710d",
        "type": "tabs",
        "children": [
          {
            "id": "425d62a01a52c9d7",
            "type": "leaf",
            "state": {
              "type": "backlink",
              "state": {
                "file": "Japaneese/Okkonomeyaki.md",
                "collapseAll": false,
                "extraContext": false,
                "sortOrder": "alphabetical",
                "showSearch": false,
                "searchQuery": "",
                "backlinkCollapsed": false,
                "unlinkedCollapsed": true
              },
              "icon": "links-coming-in",
              "title": "Backlinks for Okkonomeyaki"
            }
          },
          {
            "id": "623ed769a5b32485",
            "type": "leaf",
            "state": {
              "type": "outgoing-link",
              "state": {
                "file": "Japaneese/Okkonomeyaki.md",
                "linksCollapsed": false,
                "unlinkedCollapsed": true
              },
              "icon": "links-going-out",
              "title": "Outgoing links from Okkonomeyaki"
            }
          },
          {
            "id": "d3871041d46c169f",
            "type": "leaf",
            "state": {
              "type": "tag",
              "state": {
                "sortOrder": "frequency",
                "useHierarchy": true,
                "showSearch": false,
                "searchQuery": ""
              },
              "icon": "lucide-tags",
              "title": "Tags"
            }
          },
          {
            "id": "659b275dce2d0a42",
            "type": "leaf",
            "state": {
              "type": "outline",
              "state": {
                "file": "Japaneese/Okkonomeyaki.md",
                "followCursor": false,
                "showSearch": false,
                "searchQuery": ""
              },
              "icon": "lucide-list",
              "title": "Outline of Okkonomeyaki"
            }
          }
        ]
      }
    ],
    "direction": "horizontal",
    "width": 300,
    "collapsed": true
  },
  "left-ribbon": {
    "hiddenItems": {
      "switcher:Open quick switcher": false,
      "graph:Open graph view": false,
      "canvas:Create new canvas": false,
      "daily-notes:Open today's daily note": false,
      "templates:Insert template": false,
      "command-palette:Open command palette": false
    }
  },
  "active": "0c526fe2d45a6321",
  "lastOpenFiles": [
    "create a link.md",
    "Japaneese/Okkonomeyaki.md",
    "Japaneese",
    "Welcome.md"
  ]
}